lightcone/__init__.py
lightcone/app.py
lightcone/models.py
lightcone-0.1.0.dist-info/LICENSE
lightcone-0.1.0.dist-info/METADATA
lightcone-0.1.0.dist-info/WHEEL
lightcone-0.1.0.dist-info/top_level.txt
lightcone-0.1.0.dist-info/RECORD
