Metadata-Version: 2.1
Name: lightcone
Version: 0.1.0
Summary: A framework to explore the latent space of autoencoders implemented in torch
Home-page: https://github.com/windisch/lightcone
Author: Tobias Windisch
Author-email: tobias.windisch@hs-kempten.de
License: Apache-2.0
Keywords: graphical models
Requires-Python: >=3.8.0
License-File: LICENSE
Requires-Dist: numpy (>=1.23.0)
Requires-Dist: pandas (>=1.5.0)
Requires-Dist: torch
Requires-Dist: plotly
Requires-Dist: dash
Requires-Dist: jupyter-dash
